icalendar/__init__.py
icalendar/_version.py
icalendar/alarms.py
icalendar/attr.py
icalendar/cal.py
icalendar/caselessdict.py
icalendar/cli.py
icalendar/enums.py
icalendar/error.py
icalendar/param.py
icalendar/parser.py
icalendar/parser_tools.py
icalendar/prop.py
icalendar/tools.py
icalendar/version.py
icalendar/tests/__init__.py
icalendar/tests/conftest.py
icalendar/tests/test_bom_calendar.py
icalendar/tests/test_cli_tool.py
icalendar/tests/test_components_break_on_bad_ics.py
icalendar/tests/test_create_release.sh
icalendar/tests/test_encoding.py
icalendar/tests/test_equality.py
icalendar/tests/test_examples.py
icalendar/tests/test_icalendar.py
icalendar/tests/test_issue_116.py
icalendar/tests/test_issue_165_missing_event.py
icalendar/tests/test_issue_168_parsing_invalid_calendars_no_warning.py
icalendar/tests/test_issue_218_parse_calendar.py
icalendar/tests/test_issue_27_period.py
icalendar/tests/test_issue_318_skip_default_parameters.py
icalendar/tests/test_issue_322_single_strings_characters_split_into_multiple_categories.py
icalendar/tests/test_issue_348_exception_parsing_value.py
icalendar/tests/test_issue_350.py
icalendar/tests/test_issue_500_vboolean_for_parameter.py
icalendar/tests/test_issue_557_encode_native_parameters.py
icalendar/tests/test_issue_662_component_properties.py
icalendar/tests/test_issue_716_alarm_time_computation.py
icalendar/tests/test_issue_722_generate_vtimezone.py
icalendar/tests/test_issue_798_property_parameters.py
icalendar/tests/test_issue_802.py
icalendar/tests/test_multiple.py
icalendar/tests/test_oss_fuzz_errors.py
icalendar/tests/test_parsing.py
icalendar/tests/test_period.py
icalendar/tests/test_property_params.py
icalendar/tests/test_pytz_zoneinfo_integration.py
icalendar/tests/test_recurrence.py
icalendar/tests/test_rfc_6868.py
icalendar/tests/test_rfc_7529.py
icalendar/tests/test_rfc_7986.py
icalendar/tests/test_rfc_7986_categories.py
icalendar/tests/test_rfc_9074.py
icalendar/tests/test_time.py
icalendar-6.2.0.dist-info/METADATA
icalendar-6.2.0.dist-info/WHEEL
icalendar-6.2.0.dist-info/entry_points.txt
icalendar-6.2.0.dist-info/licenses/LICENSE.rst
icalendar-6.2.0.dist-info/RECORD
