Metadata-Version: 2.4
Name: icalendar
Version: 6.2.0
Summary: iCalendar parser/generator
Project-URL: Homepage, https://icalendar.readthedocs.io/
Project-URL: Repository, https://github.com/collective/icalendar/
Project-URL: source_archive, https://github.com/collective/icalendar/archive/07d49e75cf5716aeed3f3c2fc41c41f4733fcecc.zip
Project-URL: Issues, https://github.com/collective/icalendar/issues
Project-URL: Documentation, https://icalendar.readthedocs.io/
Project-URL: Changelog, https://icalendar.readthedocs.io/en/latest/changelog.html
Author-email: Plone Foundation <plone-developers@lists.sourceforge.net>
Maintainer: Christian Geier
Maintainer-email: Nicco Kunzmann <niccokunzmann@rambler.ru>, Jaca <vitouejj@gmail.com>
License-Expression: BSD-2-Clause
License-File: LICENSE.rst
Keywords: calendar,calendaring,event,ical,icalendar,journal,recurring,rfc5545,todo
Classifier: Development Status :: 5 - Production/Stable
Classifier: Intended Audience :: Developers
Classifier: License :: OSI Approved :: BSD License
Classifier: Operating System :: OS Independent
Classifier: Programming Language :: Python
Classifier: Programming Language :: Python :: 3.8
Classifier: Programming Language :: Python :: 3.9
Classifier: Programming Language :: Python :: 3.10
Classifier: Programming Language :: Python :: 3.11
Classifier: Programming Language :: Python :: 3.12
Classifier: Programming Language :: Python :: 3.13
Classifier: Programming Language :: Python :: Implementation :: CPython
Classifier: Programming Language :: Python :: Implementation :: PyPy
Requires-Python: >=3.8
Requires-Dist: backports-zoneinfo; python_version < '3.9'
Requires-Dist: python-dateutil
Requires-Dist: tzdata
Provides-Extra: test
Requires-Dist: coverage; extra == 'test'
Requires-Dist: hypothesis; extra == 'test'
Requires-Dist: pytest; extra == 'test'
Requires-Dist: pytz; extra == 'test'
